{
  "id": "1671155539630493702",
  "id_str": "1671155539630493702",
  "created_at": "Tue Jun 20 13:58:23 +0000 2023",
  "text": "My newsletter didn't go out on time today for the first time in about 2 months, since I started focusing on publishing consistently.\n\nUnfortunately, this sickness I'm trying to fight off got the better of me. \n\nGoing to try to get it out for tomorrow.",
  "in_reply_to_status_id": null,
  "in_reply_to_status_id_str": null,
  "in_reply_to_user_id": null,
  "in_reply_to_user_id_str": null,
  "in_reply_to_screen_name": null,
  "user": {},
  "retweet_count": "0",
  "favorite_count": "6",
  "favorited": false,
  "retweeted": false,
  "entities": {
    "hashtags": [],
    "symbols": [],
    "user_mentions": [],
    "urls": []
  },
  "lang": "en"
}