{
  "id": "1759251127470592238",
  "id_str": "1759251127470592238",
  "created_at": "Sun Feb 18 16:18:48 +0000 2024",
  "text": "Data is the demon that always lies, whispering the things in your ear that you want to hear.\n\nThe key with data is to listen to what it ISN'T saying.\n\nThat's where the truth lives. https://t.co/bTg4onhRuJ",
  "in_reply_to_status_id": null,
  "in_reply_to_status_id_str": null,
  "in_reply_to_user_id": null,
  "in_reply_to_user_id_str": null,
  "in_reply_to_screen_name": null,
  "user": {},
  "retweet_count": "1",
  "favorite_count": "2",
  "favorited": false,
  "retweeted": false,
  "entities": {
    "hashtags": [],
    "symbols": [],
    "user_mentions": [],
    "urls": [
      {
        "url": "https://t.co/bTg4onhRuJ",
        "expanded_url": "https://x.com/bryancsk/status/1759057499611967504",
        "display_url": "x.com/bryancsk/statu…",
        "indices": [
          "181",
          "204"
        ]
      }
    ]
  },
  "lang": "en"
}