{
  "id": "1617535211201351684",
  "id_str": "1617535211201351684",
  "created_at": "Mon Jan 23 14:50:21 +0000 2023",
  "text": "Probably the biggest impact of Generative AI so far:\n\nExtreme Verticalization will be too limited to be successful.\n\nWider is better when using AI.\n\nOf course, too wide is also a problem, so don't shift to being completely horizontal either.\n\nLook for the balance.",
  "in_reply_to_status_id": null,
  "in_reply_to_status_id_str": null,
  "in_reply_to_user_id": null,
  "in_reply_to_user_id_str": null,
  "in_reply_to_screen_name": null,
  "user": {},
  "retweet_count": "0",
  "favorite_count": "3",
  "favorited": false,
  "retweeted": false,
  "entities": {
    "hashtags": [],
    "symbols": [],
    "user_mentions": [],
    "urls": []
  },
  "lang": "en"
}