{
  "id": "1767203318948938119",
  "id_str": "1767203318948938119",
  "created_at": "Mon Mar 11 14:57:58 +0000 2024",
  "text": "If you examine the most successful people in history, you'll notice a few specific trends:\n\n1. Groups of people getting together that all end up being high performers. \nWhether ancient Greek philosophers or Silicon Valley, there are always groups coming together to produce the…",
  "in_reply_to_status_id": null,
  "in_reply_to_status_id_str": null,
  "in_reply_to_user_id": null,
  "in_reply_to_user_id_str": null,
  "in_reply_to_screen_name": null,
  "user": {},
  "retweet_count": "0",
  "favorite_count": "0",
  "favorited": false,
  "retweeted": false,
  "entities": {
    "hashtags": [],
    "symbols": [],
    "user_mentions": [],
    "urls": []
  },
  "lang": "en"
}