{
  "id": "1848780015288156591",
  "id_str": "1848780015288156591",
  "created_at": "Tue Oct 22 17:34:38 +0000 2024",
  "text": "Labels help us to find the people we reaonate with. \n\nThey should be a search term, not an identity. https://t.co/z8rqkaHJaI",
  "in_reply_to_status_id": null,
  "in_reply_to_status_id_str": null,
  "in_reply_to_user_id": null,
  "in_reply_to_user_id_str": null,
  "in_reply_to_screen_name": null,
  "user": {},
  "retweet_count": "0",
  "favorite_count": "0",
  "favorited": false,
  "retweeted": false,
  "entities": {
    "hashtags": [],
    "symbols": [],
    "user_mentions": [],
    "urls": [
      {
        "url": "https://t.co/z8rqkaHJaI",
        "expanded_url": "https://x.com/dvassallo/status/1848759269002514516",
        "display_url": "x.com/dvassallo/stat…",
        "indices": [
          "101",
          "124"
        ]
      }
    ]
  },
  "lang": "en"
}