{
  "id": "1678765667984769027",
  "id_str": "1678765667984769027",
  "created_at": "Tue Jul 11 13:58:19 +0000 2023",
  "text": "Building a Zapier integration and it's actually way easier than I thought it would be\n\nShould have v1 up this morning for a group to test, but even the planned improvements should be straightforward. \n\nImpressed with the ease, honestly.",
  "in_reply_to_status_id": null,
  "in_reply_to_status_id_str": null,
  "in_reply_to_user_id": null,
  "in_reply_to_user_id_str": null,
  "in_reply_to_screen_name": null,
  "user": {},
  "retweet_count": "0",
  "favorite_count": "1",
  "favorited": false,
  "retweeted": false,
  "entities": {
    "hashtags": [],
    "symbols": [],
    "user_mentions": [],
    "urls": []
  },
  "lang": "en"
}