{
  "id": "1858571487940407378",
  "id_str": "1858571487940407378",
  "created_at": "Mon Nov 18 18:02:27 +0000 2024",
  "text": "If you don't believe me or don't get it, I do have time to try to convince you. But you'll need to join my university.\n\nhttps://t.co/go9BZMuhNW https://t.co/38Yiu2K2vj",
  "in_reply_to_status_id": null,
  "in_reply_to_status_id_str": null,
  "in_reply_to_user_id": null,
  "in_reply_to_user_id_str": null,
  "in_reply_to_screen_name": null,
  "user": {},
  "retweet_count": "1",
  "favorite_count": "1",
  "favorited": false,
  "retweeted": false,
  "entities": {
    "hashtags": [],
    "symbols": [],
    "user_mentions": [],
    "urls": [
      {
        "url": "https://t.co/go9BZMuhNW",
        "expanded_url": "https://www.buildinpublicuniversity.com/are-you-a-hitchhiker/",
        "display_url": "buildinpublicuniversity.com/are-you-a-hitc…",
        "indices": [
          "120",
          "143"
        ]
      },
      {
        "url": "https://t.co/38Yiu2K2vj",
        "expanded_url": "https://x.com/koto9x/status/1858562322450575723",
        "display_url": "x.com/koto9x/status/…",
        "indices": [
          "144",
          "167"
        ]
      }
    ]
  },
  "lang": "en"
}