{
  "tweet": {
    "edit_info": {
      "initial": {
        "editTweetIds": [
          "1855301107364315358"
        ],
        "editableUntil": "2024-11-09T18:27:08.000Z",
        "editsRemaining": "5",
        "isEditEligible": true
      }
    },
    "retweeted": false,
    "source": "<a href=\"https://mobile.twitter.com\" rel=\"nofollow\">Twitter Web App</a>",
    "entities": {
      "hashtags": [],
      "symbols": [],
      "user_mentions": [],
      "urls": []
    },
    "display_text_range": [
      "0",
      "125"
    ],
    "favorite_count": "1",
    "id_str": "1855301107364315358",
    "truncated": false,
    "retweet_count": "0",
    "id": "1855301107364315358",
    "created_at": "Sat Nov 09 17:27:08 +0000 2024",
    "favorited": false,
    "full_text": "The biggest issue with the world right now is that everything is a global competition.\n\nThis is also the biggest opportunity.",
    "lang": "en"
  }
}