{
  "tweet": {
    "edit_info": {
      "initial": {
        "editTweetIds": [
          "1943370964269478246"
        ],
        "editableUntil": "2025-07-10T19:05:18.000Z",
        "editsRemaining": "5",
        "isEditEligible": true
      }
    },
    "retweeted": false,
    "source": "<a href=\"http://twitter.com/download/iphone\" rel=\"nofollow\">Twitter for iPhone</a>",
    "entities": {
      "hashtags": [],
      "symbols": [],
      "user_mentions": [],
      "urls": [
        {
          "url": "https://t.co/dm2qj9hmim",
          "expanded_url": "https://x.com/djcows/status/1943334800561181137",
          "display_url": "x.com/djcows/status/…",
          "indices": [
            "83",
            "106"
          ]
        }
      ]
    },
    "display_text_range": [
      "0",
      "106"
    ],
    "favorite_count": "1",
    "id_str": "1943370964269478246",
    "truncated": false,
    "retweet_count": "0",
    "id": "1943370964269478246",
    "possibly_sensitive": false,
    "created_at": "Thu Jul 10 18:05:18 +0000 2025",
    "favorited": false,
    "full_text": "Yes and no. There’s always work to be done,  but the “job” part will be automated. https://t.co/dm2qj9hmim",
    "lang": "en"
  }
}