{
  "id": "1574034784577273856",
  "id_str": "1574034784577273856",
  "created_at": "Sun Sep 25 13:55:11 +0000 2022",
  "text": "Going to try to get a new issue of the SaaS Factory out today. It's a tough one to write, too. \n\nGonna share details of a big screw up on my part. Not the most comfortable feeling, but that's why I'm doing it.",
  "in_reply_to_status_id": null,
  "in_reply_to_status_id_str": null,
  "in_reply_to_user_id": null,
  "in_reply_to_user_id_str": null,
  "in_reply_to_screen_name": null,
  "user": {},
  "retweet_count": "0",
  "favorite_count": "3",
  "favorited": false,
  "retweeted": false,
  "entities": {
    "hashtags": [],
    "symbols": [],
    "user_mentions": [],
    "urls": []
  },
  "lang": "en"
}