{
  "id": "1942035797038780877",
  "id_str": "1942035797038780877",
  "created_at": "Mon Jul 07 01:39:49 +0000 2025",
  "text": "Letting go of my bad complexity habits.\n\nDeploying a site that is simple html and javascript, with an n8n backend.\n\nI need to scale things now.",
  "in_reply_to_status_id": null,
  "in_reply_to_status_id_str": null,
  "in_reply_to_user_id": null,
  "in_reply_to_user_id_str": null,
  "in_reply_to_screen_name": null,
  "user": {},
  "retweet_count": "0",
  "favorite_count": "1",
  "favorited": false,
  "retweeted": false,
  "entities": {
    "hashtags": [],
    "symbols": [],
    "user_mentions": [],
    "urls": []
  },
  "lang": "en"
}