{
  "id": "1412239043719536645",
  "id_str": "1412239043719536645",
  "created_at": "Tue Jul 06 02:36:40 +0000 2021",
  "text": "As a corporate engineer,  I was always #1. But I'm learning how to be #2. https://t.co/a70qcqEXo5",
  "in_reply_to_status_id": null,
  "in_reply_to_status_id_str": null,
  "in_reply_to_user_id": null,
  "in_reply_to_user_id_str": null,
  "in_reply_to_screen_name": null,
  "user": {},
  "retweet_count": "1",
  "favorite_count": "6",
  "favorited": false,
  "retweeted": false,
  "entities": {
    "hashtags": [],
    "symbols": [],
    "user_mentions": [],
    "urls": [
      {
        "url": "https://t.co/a70qcqEXo5",
        "expanded_url": "https://x.com/tdinh_me/status/1411952251258621957",
        "display_url": "x.com/tdinh_me/statu…",
        "indices": [
          "74",
          "97"
        ]
      }
    ]
  },
  "lang": "en"
}