{
  "id": "1941661919946953064",
  "id_str": "1941661919946953064",
  "created_at": "Sun Jul 06 00:54:10 +0000 2025",
  "text": "Correction: autists ARE leading the way on systems change https://t.co/z0bPFXLY1z",
  "in_reply_to_status_id": null,
  "in_reply_to_status_id_str": null,
  "in_reply_to_user_id": null,
  "in_reply_to_user_id_str": null,
  "in_reply_to_screen_name": null,
  "user": {},
  "retweet_count": "0",
  "favorite_count": "3",
  "favorited": false,
  "retweeted": false,
  "entities": {
    "hashtags": [],
    "symbols": [],
    "user_mentions": [],
    "urls": [
      {
        "url": "https://t.co/z0bPFXLY1z",
        "expanded_url": "https://x.com/speakerjohnash/status/1941634388208374187",
        "display_url": "x.com/speakerjohnash…",
        "indices": [
          "58",
          "81"
        ]
      }
    ]
  },
  "lang": "en"
}