{
  "id": "cKomkalosjg",
  "channel_id": "UC_Mn3zTIipnTQ8Zy_QtXZew",
  "title": "The Myth of AI Replacing Human Workers",
  "description": "#shorts #ai #myths",
  "published_at": "2025-10-01T00:30:22+00:00",
  "view_count": 914,
  "like_count": 2,
  "comment_count": 0,
  "duration": "PT0M30S",
  "tags": [],
  "transcript": "Kind: captions Language: en No<00:00:00.320><c> matter</c><00:00:01.280><c> how</c><00:00:01.520><c> much</c><00:00:01.839><c> Silicon</c><00:00:02.240><c> Valley</c><00:00:02.639><c> tries</c> No matter how much Silicon Valley tries No matter how much Silicon Valley tries to<00:00:03.200><c> tell</c><00:00:03.360><c> us</c><00:00:03.520><c> that</c><00:00:03.760><c> they're</c><00:00:04.000><c> going</c><00:00:04.160><c> to</c> to tell us that they're going to to tell us that they're going to automate<00:00:04.720><c> us</c><00:00:04.880><c> away</c><00:00:05.120><c> and</c><00:00:05.279><c> replace</c><00:00:05.520><c> us</c><00:00:05.680><c> with</c><00:00:05.839><c> AI</c> automate us away and replace us with AI automate us away and replace us with AI agents,<00:00:06.720><c> it's</c><00:00:08.160><c> And</c><00:00:08.320><c> once</c><00:00:08.559><c> we</c><00:00:08.639><c> know</c> agents, it's And once we know agents, it's And once we know it's<00:00:09.519><c> we</c><00:00:09.760><c> could</c><00:00:09.840><c> start</c><00:00:10.080><c> building</c> it's we could start building it's we could start building systems<00:00:10.800><c> where</c><00:00:11.120><c> it</c><00:00:11.360><c> just</c><00:00:11.679><c> doesn't</c><00:00:12.160><c> try</c><00:00:12.480><c> to</c> systems where it just doesn't try to systems where it just doesn't try to make<00:00:13.360><c> that</c><00:00:13.759><c> part</c><00:00:14.080><c> be</c><00:00:14.320><c> true</c><00:00:14.639><c> because</c><00:00:14.880><c> it's</c><00:00:15.200><c> not</c> make that part be true because it's not make that part be true because it's not reality. reality. reality. But<00:00:17.119><c> if</c><00:00:17.279><c> you</c><00:00:17.440><c> look,</c><00:00:18.640><c> Silicon</c><00:00:19.039><c> Valley</c><00:00:19.279><c> is</c> But if you look, Silicon Valley is But if you look, Silicon Valley is throwing<00:00:19.840><c> a</c><00:00:20.160><c> lot</c><00:00:20.320><c> of</c><00:00:20.560><c> money</c><00:00:20.960><c> on</c><00:00:21.279><c> the</c><00:00:21.439><c> idea</c><00:00:21.840><c> of</c> throwing a lot of money on the idea of throwing a lot of money on the idea of like<00:00:23.039><c> replacing</c><00:00:23.760><c> AI</c><00:00:24.240><c> workers.</c> like replacing AI workers. like replacing AI workers. Now<00:00:27.119><c> this</c><00:00:27.519><c> is</c><00:00:27.760><c> again</c><00:00:28.480><c> arbitrage.</c>",
  "transcript_source": "youtube-subs"
}