{
  "id": "1940273181966967083",
  "id_str": "1940273181966967083",
  "created_at": "Wed Jul 02 04:55:49 +0000 2025",
  "text": "On July 4, help creators get offline more. \n\nLet's make July 4 Temporal Independence Day, where we celebrate the creators that make the internet beautiful.\n\nTo participate, pin this message at the top of your profile, along with your preferred payment method. https://t.co/mmbVlqbiQD",
  "in_reply_to_status_id": null,
  "in_reply_to_status_id_str": null,
  "in_reply_to_user_id": null,
  "in_reply_to_user_id_str": null,
  "in_reply_to_screen_name": null,
  "user": {},
  "retweet_count": "0",
  "favorite_count": "2",
  "favorited": false,
  "retweeted": false,
  "entities": {
    "user_mentions": [],
    "urls": [],
    "symbols": [],
    "media": [
      {
        "expanded_url": "https://x.com/leo_guinan/status/1940273181966967083/photo/1",
        "indices": [
          "260",
          "283"
        ],
        "url": "https://t.co/mmbVlqbiQD",
        "media_url": "http://pbs.twimg.com/media/Gu08GSEWQAA69jH.jpg",
        "id_str": "1940273093093507072",
        "id": "1940273093093507072",
        "media_url_https": "https://pbs.twimg.com/media/Gu08GSEWQAA69jH.jpg",
        "sizes": {
          "medium": {
            "w": "1024",
            "h": "1024",
            "resize": "fit"
          },
          "small": {
            "w": "680",
            "h": "680",
            "resize": "fit"
          },
          "thumb": {
            "w": "150",
            "h": "150",
            "resize": "crop"
          },
          "large": {
            "w": "1024",
            "h": "1024",
            "resize": "fit"
          }
        },
        "type": "photo",
        "display_url": "pic.x.com/mmbVlqbiQD"
      }
    ],
    "hashtags": []
  },
  "extended_entities": {
    "media": [
      {
        "expanded_url": "https://x.com/leo_guinan/status/1940273181966967083/photo/1",
        "indices": [
          "260",
          "283"
        ],
        "url": "https://t.co/mmbVlqbiQD",
        "media_url": "http://pbs.twimg.com/media/Gu08GSEWQAA69jH.jpg",
        "id_str": "1940273093093507072",
        "id": "1940273093093507072",
        "media_url_https": "https://pbs.twimg.com/media/Gu08GSEWQAA69jH.jpg",
        "sizes": {
          "medium": {
            "w": "1024",
            "h": "1024",
            "resize": "fit"
          },
          "small": {
            "w": "680",
            "h": "680",
            "resize": "fit"
          },
          "thumb": {
            "w": "150",
            "h": "150",
            "resize": "crop"
          },
          "large": {
            "w": "1024",
            "h": "1024",
            "resize": "fit"
          }
        },
        "type": "photo",
        "display_url": "pic.x.com/mmbVlqbiQD"
      }
    ]
  },
  "lang": "en"
}