{
  "tweet": {
    "edit_info": {
      "initial": {
        "editTweetIds": [
          "1697609599602315727"
        ],
        "editableUntil": "2023-09-01T14:57:23.000Z",
        "editsRemaining": "5",
        "isEditEligible": false
      }
    },
    "retweeted": false,
    "source": "<a href=\"https://hypefury.com\" rel=\"nofollow\">Hypefury</a>",
    "entities": {
      "hashtags": [],
      "symbols": [],
      "user_mentions": [],
      "urls": []
    },
    "display_text_range": [
      "0",
      "263"
    ],
    "favorite_count": "5",
    "id_str": "1697609599602315727",
    "truncated": false,
    "retweet_count": "0",
    "id": "1697609599602315727",
    "created_at": "Fri Sep 01 13:57:23 +0000 2023",
    "favorited": false,
    "full_text": "Googling is expensive.\n\nMe: *searches Google for a tool I need*\n\nGoogle: Yeah, I've got nothing\n\nMe: \"hmmm, guess I've got to build it\"\n\nMe: *buys domain*\n\nMe: *throws domain onto the pile of other domains that are things I'm going to definitely eventually build*",
    "lang": "en"
  }
}