{
  "id": "1920620577301102712",
  "id_str": "1920620577301102712",
  "created_at": "Thu May 08 23:23:23 +0000 2025",
  "text": "New pope is Catholic^n https://t.co/CNnwDWxa2n",
  "in_reply_to_status_id": null,
  "in_reply_to_status_id_str": null,
  "in_reply_to_user_id": null,
  "in_reply_to_user_id_str": null,
  "in_reply_to_screen_name": null,
  "user": {},
  "retweet_count": "0",
  "favorite_count": "1",
  "favorited": false,
  "retweeted": false,
  "entities": {
    "hashtags": [],
    "symbols": [],
    "user_mentions": [],
    "urls": [
      {
        "url": "https://t.co/CNnwDWxa2n",
        "expanded_url": "https://x.com/LongFormMath/status/1920545813987483707",
        "display_url": "x.com/LongFormMath/s…",
        "indices": [
          "23",
          "46"
        ]
      }
    ]
  },
  "lang": "en"
}