{
  "id": "1488220891880247302",
  "id_str": "1488220891880247302",
  "created_at": "Mon Jan 31 18:41:25 +0000 2022",
  "text": "Realized that I haven't seen anyone actually say the most interesting part of web 3 out loud yet. \n\nThink I've got an idea for my next video.",
  "in_reply_to_status_id": null,
  "in_reply_to_status_id_str": null,
  "in_reply_to_user_id": null,
  "in_reply_to_user_id_str": null,
  "in_reply_to_screen_name": null,
  "user": {},
  "retweet_count": "1",
  "favorite_count": "4",
  "favorited": false,
  "retweeted": false,
  "entities": {
    "hashtags": [],
    "symbols": [],
    "user_mentions": [],
    "urls": []
  },
  "lang": "en"
}