{
  "id": "1527740953301241868",
  "id_str": "1527740953301241868",
  "created_at": "Fri May 20 20:00:01 +0000 2022",
  "text": "Can anybody help Dave fill this slot? Please tag anyone who might know somebody! https://t.co/hmmDI8dMyB",
  "in_reply_to_status_id": null,
  "in_reply_to_status_id_str": null,
  "in_reply_to_user_id": null,
  "in_reply_to_user_id_str": null,
  "in_reply_to_screen_name": null,
  "user": {},
  "retweet_count": "1",
  "favorite_count": "3",
  "favorited": false,
  "retweeted": false,
  "entities": {
    "hashtags": [],
    "symbols": [],
    "user_mentions": [],
    "urls": [
      {
        "url": "https://t.co/hmmDI8dMyB",
        "expanded_url": "https://x.com/MindsetByDave/status/1527739871229526016",
        "display_url": "x.com/MindsetByDave/…",
        "indices": [
          "81",
          "104"
        ]
      }
    ]
  },
  "lang": "en"
}