{
  "tweet": {
    "edit_info": {
      "initial": {
        "editTweetIds": [
          "1406380465603371008"
        ],
        "editableUntil": "2021-06-19T23:36:46.942Z",
        "editsRemaining": "5",
        "isEditEligible": true
      }
    },
    "retweeted": false,
    "source": "<a href=\"https://mobile.twitter.com\" rel=\"nofollow\">Twitter Web App</a>",
    "entities": {
      "hashtags": [],
      "symbols": [],
      "user_mentions": [],
      "urls": []
    },
    "display_text_range": [
      "0",
      "75"
    ],
    "favorite_count": "0",
    "in_reply_to_status_id_str": "1406380090297044997",
    "id_str": "1406380465603371008",
    "in_reply_to_user_id": "104512758",
    "truncated": false,
    "retweet_count": "0",
    "id": "1406380465603371008",
    "in_reply_to_status_id": "1406380090297044997",
    "created_at": "Sat Jun 19 22:36:46 +0000 2021",
    "favorited": false,
    "full_text": "@steve_asbell Watched it this morning with the family. I really enjoyed it.",
    "lang": "en",
    "in_reply_to_user_id_str": "104512758"
  }
}