{
  "tweet": {
    "edit_info": {
      "initial": {
        "editTweetIds": [
          "1485088712543412224"
        ],
        "editableUntil": "2022-01-23T04:15:15.341Z",
        "editsRemaining": "5",
        "isEditEligible": true
      }
    },
    "retweeted": false,
    "source": "<a href=\"http://twitter.com/download/android\" rel=\"nofollow\">Twitter for Android</a>",
    "entities": {
      "hashtags": [],
      "symbols": [],
      "user_mentions": [],
      "urls": [
        {
          "url": "https://t.co/1k6rLuaGn7",
          "expanded_url": "https://x.com/amandanat/status/1484979786875236353",
          "display_url": "x.com/amandanat/stat…",
          "indices": [
            "143",
            "166"
          ]
        }
      ]
    },
    "display_text_range": [
      "0",
      "166"
    ],
    "favorite_count": "3",
    "id_str": "1485088712543412224",
    "truncated": false,
    "retweet_count": "0",
    "id": "1485088712543412224",
    "possibly_sensitive": false,
    "created_at": "Sun Jan 23 03:15:15 +0000 2022",
    "favorited": false,
    "full_text": "The gold sits beneath the surface a lot of times.\n\nHow often do you peek into the conversations people have? \n\nHow often are you part of them? https://t.co/1k6rLuaGn7",
    "lang": "en"
  }
}