{
  "id": "1388290993531854857",
  "id_str": "1388290993531854857",
  "created_at": "Sat May 01 00:35:40 +0000 2021",
  "text": "Time for another #BuildInPublicTherapySession!\n\nToday, we're going to talk about pain. Specifically, this week for #ODCC1, we were asked to think about our students' pain points and where we could help them. Turns out, for #NeurodiverseEntrepreneurs, I think I have a really",
  "in_reply_to_status_id": null,
  "in_reply_to_status_id_str": null,
  "in_reply_to_user_id": null,
  "in_reply_to_user_id_str": null,
  "in_reply_to_screen_name": null,
  "user": {},
  "retweet_count": "1",
  "favorite_count": "5",
  "favorited": false,
  "retweeted": false,
  "entities": {
    "hashtags": [
      {
        "text": "BuildInPublicTherapySession",
        "indices": [
          "17",
          "45"
        ]
      },
      {
        "text": "ODCC1",
        "indices": [
          "115",
          "121"
        ]
      },
      {
        "text": "NeurodiverseEntrepreneurs",
        "indices": [
          "223",
          "249"
        ]
      }
    ],
    "symbols": [],
    "user_mentions": [],
    "urls": []
  },
  "lang": "en"
}