{
  "id": "1547251465605074947",
  "id_str": "1547251465605074947",
  "created_at": "Wed Jul 13 16:07:50 +0000 2022",
  "text": "Huh, #buildinginpublic is currently trending.\n\nI'm totally going to take credit for that (even though I never tweet with that particular hashtag...).\n\nBuild In Public University is taking off before it even started!\n\n#FunChaos",
  "in_reply_to_status_id": null,
  "in_reply_to_status_id_str": null,
  "in_reply_to_user_id": null,
  "in_reply_to_user_id_str": null,
  "in_reply_to_screen_name": null,
  "user": {},
  "retweet_count": "0",
  "favorite_count": "4",
  "favorited": false,
  "retweeted": false,
  "entities": {
    "hashtags": [
      {
        "text": "buildinginpublic",
        "indices": [
          "5",
          "22"
        ]
      },
      {
        "text": "FunChaos",
        "indices": [
          "217",
          "226"
        ]
      }
    ],
    "symbols": [],
    "user_mentions": [],
    "urls": []
  },
  "lang": "en"
}