{
  "id": "1813963315162632543",
  "id_str": "1813963315162632543",
  "created_at": "Thu Jul 18 15:45:30 +0000 2024",
  "text": "I've definitely thought about the \"making tools people-shaped\", but now I can connect it to research in the \"cognitive ergonomics\" space.\n\nFunny how these types of words can mean the same thing, but the connection of them can create brand new webs of knowledge. https://t.co/XB5sDExsZl",
  "in_reply_to_status_id": null,
  "in_reply_to_status_id_str": null,
  "in_reply_to_user_id": null,
  "in_reply_to_user_id_str": null,
  "in_reply_to_screen_name": null,
  "user": {},
  "retweet_count": "0",
  "favorite_count": "2",
  "favorited": false,
  "retweeted": false,
  "entities": {
    "hashtags": [],
    "symbols": [],
    "user_mentions": [],
    "urls": [
      {
        "url": "https://t.co/XB5sDExsZl",
        "expanded_url": "https://x.com/visakanv/status/1813960741466308711",
        "display_url": "x.com/visakanv/statu…",
        "indices": [
          "262",
          "285"
        ]
      }
    ]
  },
  "lang": "en"
}