{
  "tweet": {
    "edit_info": {
      "initial": {
        "editTweetIds": [
          "1458450159344525316"
        ],
        "editableUntil": "2021-11-10T16:03:09.338Z",
        "editsRemaining": "5",
        "isEditEligible": true
      }
    },
    "retweeted": false,
    "source": "<a href=\"https://hypefury.com\" rel=\"nofollow\">Hypefury</a>",
    "entities": {
      "hashtags": [],
      "symbols": [],
      "user_mentions": [],
      "urls": []
    },
    "display_text_range": [
      "0",
      "243"
    ],
    "favorite_count": "3",
    "id_str": "1458450159344525316",
    "truncated": false,
    "retweet_count": "2",
    "id": "1458450159344525316",
    "created_at": "Wed Nov 10 15:03:09 +0000 2021",
    "favorited": false,
    "full_text": "Let me know if you have an email list of 500-5000 subscribers and a Twitter following that you are trying to manage. I'm working on setting up a pilot program for the next iteration of @feathercrm and want to get 5 people who fit this profile.",
    "lang": "en"
  }
}