{
  "id": "1749426933333389759",
  "id_str": "1749426933333389759",
  "created_at": "Mon Jan 22 13:40:58 +0000 2024",
  "text": "Have you ever wondered why the economy seems to serve businesses more than people? \n\nIt’s a perplexing issue. Our economy centers the business as the value creation engine and rewards businesses accordingly through profits and growth. But when you think about it, businesses don’t…",
  "in_reply_to_status_id": null,
  "in_reply_to_status_id_str": null,
  "in_reply_to_user_id": null,
  "in_reply_to_user_id_str": null,
  "in_reply_to_screen_name": null,
  "user": {},
  "retweet_count": "0",
  "favorite_count": "0",
  "favorited": false,
  "retweeted": false,
  "entities": {
    "hashtags": [],
    "symbols": [],
    "user_mentions": [],
    "urls": []
  },
  "lang": "en"
}