{
  "id": "1883238549581176887",
  "id_str": "1883238549581176887",
  "created_at": "Sat Jan 25 19:40:33 +0000 2025",
  "text": "*taps the sign *\n\nThis a function of economic risk being pushed into predictability risk at the individual level and when people fear for their future they don’t take risks. \n\nWe’ve optimized the risk out of the economy by making “risk” predictable. https://t.co/sQ6BHOSHvE",
  "in_reply_to_status_id": null,
  "in_reply_to_status_id_str": null,
  "in_reply_to_user_id": null,
  "in_reply_to_user_id_str": null,
  "in_reply_to_screen_name": null,
  "user": {},
  "retweet_count": "0",
  "favorite_count": "1",
  "favorited": false,
  "retweeted": false,
  "entities": {
    "hashtags": [],
    "symbols": [],
    "user_mentions": [],
    "urls": [
      {
        "url": "https://t.co/sQ6BHOSHvE",
        "expanded_url": "https://x.com/signulll/status/1883211791372554573",
        "display_url": "x.com/signulll/statu…",
        "indices": [
          "250",
          "273"
        ]
      }
    ]
  },
  "lang": "en"
}