{
  "tweet": {
    "edit_info": {
      "initial": {
        "editTweetIds": [
          "1474385445937377283"
        ],
        "editableUntil": "2021-12-24T15:24:17.725Z",
        "editsRemaining": "5",
        "isEditEligible": true
      }
    },
    "retweeted": false,
    "source": "<a href=\"http://twitter.com/download/android\" rel=\"nofollow\">Twitter for Android</a>",
    "entities": {
      "hashtags": [],
      "symbols": [],
      "user_mentions": [],
      "urls": []
    },
    "display_text_range": [
      "0",
      "213"
    ],
    "favorite_count": "1",
    "id_str": "1474385445937377283",
    "truncated": false,
    "retweet_count": "0",
    "id": "1474385445937377283",
    "created_at": "Fri Dec 24 14:24:17 +0000 2021",
    "favorited": false,
    "full_text": "Final Christmas gift acquired. Little more last minute than I tend to like, but got it.\n\nGift to myself: I'm not going to do any work today or tomorrow. \n\nIt's not going to be easy. But it's time to rest a little.",
    "lang": "en"
  }
}