{
  "tweet": {
    "edit_info": {
      "initial": {
        "editTweetIds": [
          "1474192161621041155"
        ],
        "editableUntil": "2021-12-24T02:36:15.153Z",
        "editsRemaining": "5",
        "isEditEligible": true
      }
    },
    "retweeted": false,
    "source": "<a href=\"http://twitter.com/download/android\" rel=\"nofollow\">Twitter for Android</a>",
    "entities": {
      "hashtags": [],
      "symbols": [],
      "user_mentions": [],
      "urls": []
    },
    "display_text_range": [
      "0",
      "265"
    ],
    "favorite_count": "2",
    "id_str": "1474192161621041155",
    "truncated": false,
    "retweet_count": "2",
    "id": "1474192161621041155",
    "created_at": "Fri Dec 24 01:36:15 +0000 2021",
    "favorited": false,
    "full_text": "Ok, a few new features live on @feathercrm .\n\n1. Instead of putting in a twitter profile url, you can just type their screen name. \n\n2. Added a column that shows the top 10 accounts that have interacted with you in the past week. \n\n3. Some behind the scenes changes",
    "lang": "en"
  }
}