{
  "id": "1356765975014748163",
  "id_str": "1356765975014748163",
  "created_at": "Wed Feb 03 00:46:30 +0000 2021",
  "text": "This is not the right way to go with advertising.... https://t.co/QmaFZn0hkr",
  "in_reply_to_status_id": null,
  "in_reply_to_status_id_str": null,
  "in_reply_to_user_id": null,
  "in_reply_to_user_id_str": null,
  "in_reply_to_screen_name": null,
  "user": {},
  "retweet_count": "0",
  "favorite_count": "1",
  "favorited": false,
  "retweeted": false,
  "entities": {
    "hashtags": [],
    "symbols": [],
    "user_mentions": [],
    "urls": [
      {
        "url": "https://t.co/QmaFZn0hkr",
        "expanded_url": "https://x.com/VentureBeat/status/1356765607509848065",
        "display_url": "x.com/VentureBeat/st…",
        "indices": [
          "53",
          "76"
        ]
      }
    ]
  },
  "lang": "en"
}