{
  "id": "1592320055261691904",
  "id_str": "1592320055261691904",
  "created_at": "Tue Nov 15 00:54:19 +0000 2022",
  "text": "Ok, wrote a blog about this. Here's my recommendation:\nhttps://t.co/yIxrj2tTco https://t.co/RMxYBJwueS",
  "in_reply_to_status_id": null,
  "in_reply_to_status_id_str": null,
  "in_reply_to_user_id": null,
  "in_reply_to_user_id_str": null,
  "in_reply_to_screen_name": null,
  "user": {},
  "retweet_count": "0",
  "favorite_count": "1",
  "favorited": false,
  "retweeted": false,
  "entities": {
    "hashtags": [],
    "symbols": [],
    "user_mentions": [],
    "urls": [
      {
        "url": "https://t.co/yIxrj2tTco",
        "expanded_url": "https://www.howtoscaleyourself.com/owning-your-social-network/",
        "display_url": "howtoscaleyourself.com/owning-your-so…",
        "indices": [
          "55",
          "78"
        ]
      },
      {
        "url": "https://t.co/RMxYBJwueS",
        "expanded_url": "https://x.com/eggs_mayhem/status/1591225884488310784",
        "display_url": "x.com/eggs_mayhem/st…",
        "indices": [
          "79",
          "102"
        ]
      }
    ]
  },
  "lang": "en"
}