{
  "id": "1685341874964324352",
  "id_str": "1685341874964324352",
  "created_at": "Sat Jul 29 17:29:49 +0000 2023",
  "text": "Thoughts? https://t.co/SKuYMtR1np",
  "in_reply_to_status_id": null,
  "in_reply_to_status_id_str": null,
  "in_reply_to_user_id": null,
  "in_reply_to_user_id_str": null,
  "in_reply_to_screen_name": null,
  "user": {},
  "retweet_count": "0",
  "favorite_count": "0",
  "favorited": false,
  "retweeted": false,
  "entities": {
    "hashtags": [],
    "symbols": [],
    "user_mentions": [],
    "urls": [
      {
        "url": "https://t.co/SKuYMtR1np",
        "expanded_url": "https://x.com/thisiskp_/status/1685338790083366912",
        "display_url": "x.com/thisiskp_/stat…",
        "indices": [
          "10",
          "33"
        ]
      }
    ]
  },
  "lang": "en"
}