{
  "id": "1595431782274719744",
  "id_str": "1595431782274719744",
  "created_at": "Wed Nov 23 14:59:13 +0000 2022",
  "text": "New idea (ok, old idea coming back around, if I'm honest, but with a new angle).\n\nA couple of conversations this week sparked some thoughts that I can't stop thinking about.\n\nSo I'm going to act on them this weekend.\n\nIf you're curious about the future, this is for you.",
  "in_reply_to_status_id": null,
  "in_reply_to_status_id_str": null,
  "in_reply_to_user_id": null,
  "in_reply_to_user_id_str": null,
  "in_reply_to_screen_name": null,
  "user": {},
  "retweet_count": "0",
  "favorite_count": "2",
  "favorited": false,
  "retweeted": false,
  "entities": {
    "hashtags": [],
    "symbols": [],
    "user_mentions": [],
    "urls": []
  },
  "lang": "en"
}